sqlact/__init__.py
sqlact/main.py
sqlact/test_main.py
sqlact-0.0.3.dist-info/METADATA
sqlact-0.0.3.dist-info/WHEEL
sqlact-0.0.3.dist-info/entry_points.txt
sqlact-0.0.3.dist-info/top_level.txt
sqlact-0.0.3.dist-info/RECORD
