Metadata-Version: 2.1
Name: sqlact
Version: 0.0.3
Summary: A python CLI client for composing SQL queries with content-based and history-aware auto-completion
Home-page: https://github.com/ericmanzi/sqlact-cli
Author: ('Eric Manzi',)
Author-email: manzieric424a@gmail.com
License: MIT
Platform: UNKNOWN
Requires-Python: >=3.6.0
